toolstack/__init__.py
toolstack/feature/__init__.py
toolstack/feature/feature_base.py
toolstack/feature/feature_encoding.py
toolstack/text/__init__.py
toolstack/text/text_preprocessing.py
toolstack/utils/__init__.py
toolstack/utils/utility_base.py
toolstack-0.1.5.dist-info/LICENSE
toolstack-0.1.5.dist-info/METADATA
toolstack-0.1.5.dist-info/WHEEL
toolstack-0.1.5.dist-info/top_level.txt
toolstack-0.1.5.dist-info/RECORD
