Metadata-Version: 2.1
Name: toolstack
Version: 0.1.5
Summary: A collection of useful tools to speed-up the data processing, cleaning and pipelining.
Home-page: https://github.com/getmykhan/toolstack
Author: Mohammed Yusuf Khan
Author-email: hello@mykhan.me
License: UNKNOWN
Keywords: toolkit,nlp,data cleaning,toolstack,data science,machine learning
Platform: UNKNOWN
Classifier: Programming Language :: Python :: 3
Classifier: License :: OSI Approved :: MIT License
Classifier: Operating System :: OS Independent
Requires-Python: >=3.7
Requires-Dist: pandas
Requires-Dist: numpy
Requires-Dist: tqdm
